selic_api/__init__.py
selic_api/selic.py
selic_api-0.0.12.dist-info/METADATA
selic_api-0.0.12.dist-info/WHEEL
selic_api-0.0.12.dist-info/RECORD
