Metadata-Version: 2.3
Name: selic_api
Version: 0.0.12
Summary: API para obtenção dos dados da SELIC.
License: MIT
Author: João Marcelo
Author-email: joaomarceloav@gmail.com
Requires-Python: >=3.8,<4.0
Classifier: License :: OSI Approved :: MIT License
Classifier: Programming Language :: Python :: 3
Classifier: Programming Language :: Python :: 3.8
Classifier: Programming Language :: Python :: 3.9
Classifier: Programming Language :: Python :: 3.10
Classifier: Programming Language :: Python :: 3.11
Classifier: Programming Language :: Python :: 3.12
Classifier: Programming Language :: Python :: 3.13
Requires-Dist: beautifulsoup4 (>=4.10.0,<5.0.0)
Requires-Dist: certifi (==2022.12.07)
Requires-Dist: python-dateutil (>=2.8.2,<3.0.0)
Requires-Dist: requests (>=2.26.0,<3.0.0)
Project-URL: Documentation, https://github.com/marceloid/selic_api
Project-URL: Homepage, https://github.com/marceloid/selic_api
Project-URL: Repository, https://github.com/marceloid/selic_api
